{
  "validation_timestamp": "2026-07-24T18:53:53.916702",
  "session_id": "isolated_2026-07-24T18:53:53.916659",
  "is_isolated": true,
  "validated_items": [
    {
      "source": "BBC News",
      "content_preview": "",
      "validation": {
        "overall_score": 100.0,
        "truth_score": 100,
        "goodness_score": 100,
        "patience_score": 100,
        "passed": true,
        "issues": [],
        "source": "BBC News",
        "timestamp": "2026-07-24T18:53:53.916722",
        "session_id": "isolated_2026-07-24T18:53:53.916659",
        "is_isolated": true
      }
    },
    {
      "source": "Reuters",
      "content_preview": "",
      "validation": {
        "overall_score": 100.0,
        "truth_score": 100,
        "goodness_score": 100,
        "patience_score": 100,
        "passed": true,
        "issues": [],
        "source": "Reuters",
        "timestamp": "2026-07-24T18:53:53.916732",
        "session_id": "isolated_2026-07-24T18:53:53.916659",
        "is_isolated": true
      }
    },
    {
      "source": "AP News",
      "content_preview": "",
      "validation": {
        "overall_score": 100.0,
        "truth_score": 100,
        "goodness_score": 100,
        "patience_score": 100,
        "passed": true,
        "issues": [],
        "source": "AP News",
        "timestamp": "2026-07-24T18:53:53.916739",
        "session_id": "isolated_2026-07-24T18:53:53.916659",
        "is_isolated": true
      }
    }
  ]
}